pylastic/__init__.py
pylastic/pylastic.py
jahia_pylastic-0.0.9.dist-info/LICENSE
jahia_pylastic-0.0.9.dist-info/METADATA
jahia_pylastic-0.0.9.dist-info/WHEEL
jahia_pylastic-0.0.9.dist-info/top_level.txt
jahia_pylastic-0.0.9.dist-info/RECORD
