Metadata-Version: 2.1
Name: jahia-pylastic
Version: 0.0.9
Summary: Interact with Jelastic API
Author-email: Jahia Cloud team <paas@jahia.com>
Project-URL: Homepage, https://github.com/jahia/pylastic
Project-URL: Bug Tracker, https://github.com/jahia/pylastic/issues
Classifier: Programming Language :: Python :: 3
Classifier: License :: OSI Approved :: MIT License
Classifier: Operating System :: OS Independent
Requires-Python: >=3.7
License-File: LICENSE
